pyttilan/__init__.py
pyttilan/backend.py
pyttilan/commands.py
pyttilan-0.2.1.dist-info/LICENSE
pyttilan-0.2.1.dist-info/METADATA
pyttilan-0.2.1.dist-info/WHEEL
pyttilan-0.2.1.dist-info/top_level.txt
pyttilan-0.2.1.dist-info/RECORD
