Metadata-Version: 2.1
Name: pyttilan
Version: 0.2.1
Summary: Library to control TTi Power Supplies over network
Home-page: https://github.com/IFAEControl/pyttilan
Author: David Roman, Otger Ballester
Author-email: ifae-control@ifae.es
License: CC0 1.0 Universal
Platform: UNKNOWN
Classifier: Development Status :: 4 - Beta
Classifier: Programming Language :: Python :: 3
Provides: pyttilan
